ommx_kipu_iskay_adapter/__init__.py
ommx_kipu_iskay_adapter/_version.py
ommx_kipu_iskay_adapter/adapter.py
ommx_kipu_iskay_adapter/exception.py
ommx_kipu_iskay_adapter-0.1.0.dist-info/licenses/LICENSE
ommx_kipu_iskay_adapter-0.1.0.dist-info/METADATA
ommx_kipu_iskay_adapter-0.1.0.dist-info/WHEEL
ommx_kipu_iskay_adapter-0.1.0.dist-info/top_level.txt
ommx_kipu_iskay_adapter-0.1.0.dist-info/RECORD
