Metadata-Version: 2.4
Name: ommx-kipu-iskay-adapter
Version: 0.1.0
Summary: OMMX adapter for Iskay quantum optimiser
Requires-Python: >=3.12
License-File: LICENSE
Requires-Dist: ommx>=2.0.0
Requires-Dist: qiskit==1.4.5
Requires-Dist: qiskit-ibm-catalog==0.9.0
Requires-Dist: qiskit-ibm-runtime==0.37.0
Requires-Dist: qiskit-qasm3-import==0.6.0
Requires-Dist: qiskit-serverless==0.25.3
Dynamic: license-file
